CONTRIBUTORS
LICENCE
MANIFEST.in
README.markdown
VERSION
example.py
setup.py
greendizer/__init__.py
greendizer/__init__.pyc
greendizer/version.py
greendizer.egg-info/PKG-INFO
greendizer.egg-info/SOURCES.txt
greendizer.egg-info/dependency_links.txt
greendizer.egg-info/requires.txt
greendizer.egg-info/top_level.txt
greendizer/clients/.DS_Store
greendizer/clients/__init__.py
greendizer/clients/base.py
greendizer/clients/config.py
greendizer/clients/dal.py
greendizer/clients/helpers.py
greendizer/clients/http.py
greendizer/clients/resources/.DS_Store
greendizer/clients/resources/__init__.py
greendizer/clients/resources/anonymous.py
greendizer/clients/resources/buyers.py
greendizer/clients/resources/sellers.py
greendizer/oauth/__init__.py
greendizer/oauth/config.py