Metadata-Version: 1.0
Name: greendizer
Version: 2.2.7
Summary: A Python wrapper of the Greendizer invoicing API.
Home-page: https://github.com/Greendizer/Greendizer-Python-Library
Author: Greendizer
Author-email: support@greendizer.com
License: The MIT Licence
